whaler/__init__.py
whaler/builtin.py
whaler/cli.py
whaler/docker.py
whaler/exceptions.py
whaler/logger.py
whaler/stack.py
orche-0.3.0.dist-info/METADATA
orche-0.3.0.dist-info/WHEEL
orche-0.3.0.dist-info/entry_points.txt
orche-0.3.0.dist-info/RECORD
