Metadata-Version: 2.4
Name: orche
Version: 0.3.0
Summary: A Python orchestrator for Docker Compose stacks
Author: Pietro Agazzi
Author-email: pietro.agazzi@prconsulting.eu
Requires-Python: >=3.10,<4
Classifier: Programming Language :: Python :: 3
Classifier: Programming Language :: Python :: 3.10
Classifier: Programming Language :: Python :: 3.11
Classifier: Programming Language :: Python :: 3.12
Classifier: Programming Language :: Python :: 3.13
Classifier: Programming Language :: Python :: 3.14
Provides-Extra: dev
Requires-Dist: GitPython (>=3.1.0)
Requires-Dist: PyYAML (>=6.0)
Requires-Dist: click (>=8.1.0)
Requires-Dist: mypy (>=1.8.0) ; extra == "dev"
Requires-Dist: pre-commit (>=4.0.0) ; extra == "dev"
Requires-Dist: pytest (>=8.0.0) ; extra == "dev"
Requires-Dist: pytest-cov (>=5.0.0) ; extra == "dev"
Requires-Dist: pytest-mock (>=3.14.0) ; extra == "dev"
Requires-Dist: pytest-timeout (>=2.3.0) ; extra == "dev"
Requires-Dist: python-dotenv (>=1.0.0)
Requires-Dist: python-on-whales (>=0.80.0,<0.81.0)
Requires-Dist: rich (>=13.0.0)
Requires-Dist: ruff (>=0.2.0) ; extra == "dev"
Requires-Dist: types-PyYAML (>=6.0) ; extra == "dev"
Requires-Dist: types-pygments (>=2.19.0) ; extra == "dev"
